README
setup.py
doggie/__init__.py
doggie/doggie.py
doggie.egg-info/PKG-INFO
doggie.egg-info/SOURCES.txt
doggie.egg-info/dependency_links.txt
doggie.egg-info/top_level.txt