Metadata-Version: 1.0
Name: doggie
Version: 0.1.6
Summary: Python library for interacting to hbase shell
Home-page: UNKNOWN
Author: hujianxin
Author-email: hujianxincn@foxmail.com
License: Apache License
Platform: UNKNOWN
